subtask/__init__.py
subtask/__subtask.py
subtask/py.typed
subtask-1.1.2.dist-info/LICENSE
subtask-1.1.2.dist-info/METADATA
subtask-1.1.2.dist-info/WHEEL
subtask-1.1.2.dist-info/RECORD
