Metadata-Version: 2.3
Name: subtask
Version: 1.1.2
Summary: A simple wrapper around `subprocess.Popen` to reduce the painfulness of running multiple processes concurrently.
License: MIT
Keywords: popen,task,process,subprocess,subtask
Author: Maddy Guthridge
Author-email: hello@maddyguthridge.com
Requires-Python: >=3.9
Classifier: Programming Language :: Python :: 3
Classifier: Intended Audience :: Developers
Classifier: License :: OSI Approved :: MIT License
Classifier: Operating System :: OS Independent
Classifier: Development Status :: 5 - Production/Stable
Classifier: Typing :: Typed
Classifier: Topic :: Software Development :: Libraries
Project-URL: Bug Tracker, https://github.com/MaddyGuthridge/subtask/issues
Project-URL: Documentation, https://github.com/MaddyGuthridge/subtask
Project-URL: Repository, https://github.com/MaddyGuthridge/subtask
